README.md
test.py
salesforce/__init__.py
salesforce/client.py
salesforce_connector.egg-info/PKG-INFO
salesforce_connector.egg-info/SOURCES.txt
salesforce_connector.egg-info/dependency_links.txt
salesforce_connector.egg-info/not-zip-safe
salesforce_connector.egg-info/requires.txt
salesforce_connector.egg-info/top_level.txt
salesforce_connector-0.0.5.dist-info/METADATA
salesforce_connector-0.0.5.dist-info/WHEEL
salesforce_connector-0.0.5.dist-info/top_level.txt
salesforce_connector-0.0.5.dist-info/RECORD
