Metadata-Version: 2.4
Name: salesforce-connector
Version: 0.0.5
Summary: A utility class to interact with SalesForce using OAuth 2.0 credentials.
Author: Mukhtar
Author-email: tabno@gmail.com
Requires-Python: >=3.10
Requires-Dist: requests
Dynamic: author
Dynamic: author-email
Dynamic: description
Dynamic: description-content-type
Dynamic: requires-dist
Dynamic: requires-python
Dynamic: summary
